[
  {
    "houseNo": "MS134774HB",
    "totalPrice": 2598.0,
    "updatedDate": "2025-04-11 09:07:32",
    "shareURL": "https://sinyi.in/o/MS134774HB/0/3",
    "displayName": "水湳經貿四房透天附車庫"
  },
  {
    "houseNo": "RS71915HB",
    "totalPrice": 1488.0,
    "updatedDate": "2025-04-11 09:07:57",
    "shareURL": "https://sinyi.in/o/RS71915HB/0/3",
    "displayName": "繁榮大三房可改4房"
  },
  {
    "houseNo": "1912960CT",
    "totalPrice": 2598.0,
    "updatedDate": "2025-04-11 09:08:35",
    "shareURL": "https://sinyi.in/o/1912960CT/0/3",
    "displayName": "近水湳經貿大面寬車庫透天"
  },
  {
    "houseNo": "1995830CT",
    "totalPrice": 1688.0,
    "updatedDate": "2025-04-11 09:06:46",
    "shareURL": "https://sinyi.in/o/1995830CT/0/3",
    "displayName": "漢口商圈一手活路透天"
  },
  {
    "houseNo": "8427AJ",
    "totalPrice": 1030.0,
    "updatedDate": "2025-04-11 09:04:08",
    "shareURL": "https://sinyi.in/o/8427AJ/0/3",
    "displayName": "崇德巴黎"
  },
  {
    "houseNo": "MS142464HB",
    "totalPrice": 1498.0,
    "updatedDate": "2025-04-11 09:05:07",
    "shareURL": "https://sinyi.in/o/MS142464HB/0/3",
    "displayName": "機捷櫻花巨人大兩房獨立平車"
  },
  {
    "houseNo": "2002402CT",
    "totalPrice": 1690.0,
    "updatedDate": "2025-04-11 09:07:16",
    "shareURL": "https://sinyi.in/o/2002402CT/0/3",
    "displayName": "曉明女中臨路透天"
  },
  {
    "houseNo": "WS35729HB",
    "totalPrice": 998.0,
    "updatedDate": "2025-04-11 09:07:52",
    "shareURL": "https://sinyi.in/o/WS35729HB/0/3",
    "displayName": "嶺東低總價五權豪門三房車位稀有"
  }
]